foundry_mcp/__init__.py
foundry_mcp/config.py
foundry_mcp/server.py
foundry_mcp/cli/__init__.py
foundry_mcp/cli/__main__.py
foundry_mcp/cli/agent.py
foundry_mcp/cli/config.py
foundry_mcp/cli/context.py
foundry_mcp/cli/flags.py
foundry_mcp/cli/logging.py
foundry_mcp/cli/main.py
foundry_mcp/cli/output.py
foundry_mcp/cli/registry.py
foundry_mcp/cli/resilience.py
foundry_mcp/cli/transcript.py
foundry_mcp/cli/commands/__init__.py
foundry_mcp/cli/commands/cache.py
foundry_mcp/cli/commands/dashboard.py
foundry_mcp/cli/commands/dev.py
foundry_mcp/cli/commands/journal.py
foundry_mcp/cli/commands/lifecycle.py
foundry_mcp/cli/commands/modify.py
foundry_mcp/cli/commands/plan.py
foundry_mcp/cli/commands/pr.py
foundry_mcp/cli/commands/review.py
foundry_mcp/cli/commands/session.py
foundry_mcp/cli/commands/specs.py
foundry_mcp/cli/commands/tasks.py
foundry_mcp/cli/commands/testing.py
foundry_mcp/cli/commands/validate.py
foundry_mcp/core/__init__.py
foundry_mcp/core/ai_consultation.py
foundry_mcp/core/cache.py
foundry_mcp/core/capabilities.py
foundry_mcp/core/concurrency.py
foundry_mcp/core/context.py
foundry_mcp/core/discovery.py
foundry_mcp/core/error_collection.py
foundry_mcp/core/error_store.py
foundry_mcp/core/feature_flags.py
foundry_mcp/core/health.py
foundry_mcp/core/intake.py
foundry_mcp/core/journal.py
foundry_mcp/core/lifecycle.py
foundry_mcp/core/llm_config.py
foundry_mcp/core/llm_patterns.py
foundry_mcp/core/llm_provider.py
foundry_mcp/core/logging_config.py
foundry_mcp/core/metrics_persistence.py
foundry_mcp/core/metrics_registry.py
foundry_mcp/core/metrics_store.py
foundry_mcp/core/modifications.py
foundry_mcp/core/naming.py
foundry_mcp/core/observability.py
foundry_mcp/core/otel.py
foundry_mcp/core/otel_stubs.py
foundry_mcp/core/pagination.py
foundry_mcp/core/progress.py
foundry_mcp/core/prometheus.py
foundry_mcp/core/rate_limit.py
foundry_mcp/core/resilience.py
foundry_mcp/core/responses.py
foundry_mcp/core/review.py
foundry_mcp/core/security.py
foundry_mcp-0.8.0.dist-info/METADATA
foundry_mcp-0.8.0.dist-info/WHEEL
foundry_mcp-0.8.0.dist-info/entry_points.txt
foundry_mcp-0.8.0.dist-info/licenses/LICENSE
foundry_mcp-0.8.0.dist-info/RECORD
