Metadata-Version: 2.4
Name: foundry-mcp
Version: 0.8.0
Summary: MCP server for SDD toolkit spec management
Project-URL: Homepage, https://github.com/tylerburleigh/foundry-mcp
Project-URL: Repository, https://github.com/tylerburleigh/foundry-mcp
Author: Tyler Burleigh
License-Expression: MIT
License-File: LICENSE
Keywords: mcp,sdd,spec-driven-development,specification
Classifier: Development Status :: 3 - Alpha
Classifier: Intended Audience :: Developers
Classifier: License :: OSI Approved :: MIT License
Classifier: Programming Language :: Python :: 3
Classifier: Programming Language :: Python :: 3.10
Classifier: Programming Language :: Python :: 3.11
Classifier: Programming Language :: Python :: 3.12
Requires-Python: >=3.10
Requires-Dist: click>=8.0.0
Requires-Dist: fastmcp>=0.1.0
Requires-Dist: filelock>=3.20.1
Requires-Dist: mcp>=1.0.0
Requires-Dist: tomli>=2.0.0; python_version < '3.11'
Provides-Extra: dashboard
Requires-Dist: pandas>=2.0.0; extra == 'dashboard'
Requires-Dist: plotly>=5.18.0; extra == 'dashboard'
Requires-Dist: streamlit>=1.28.0; extra == 'dashboard'
Provides-Extra: metrics
Requires-Dist: prometheus-client>=0.17.0; extra == 'metrics'
Provides-Extra: observability
Requires-Dist: opentelemetry-exporter-otlp>=1.20.0; extra == 'observability'
Requires-Dist: opentelemetry-sdk>=1.20.0; extra == 'observability'
Requires-Dist: prometheus-client>=0.17.0; extra == 'observability'
Provides-Extra: test
Requires-Dist: hypothesis>=6.0.0; extra == 'test'
Requires-Dist: jsonschema>=4.0.0; extra == 'test'
Requires-Dist: pytest-asyncio>=0.21.0; extra == 'test'
Requires-Dist: pytest-xdist>=3.0.0; extra == 'test'
Requires-Dist: pytest>=7.0.0; extra == 'test'
Provides-Extra: tracing
Requires-Dist: opentelemetry-exporter-otlp>=1.20.0; extra == 'tracing'
Requires-Dist: opentelemetry-sdk>=1.20.0; extra == 'tracing'
